pyprocar/__init__.py
pyprocar/_version.py
pyprocar/version.py
pyprocar/cfg/README.md
pyprocar/cfg/__init__.py
pyprocar/cfg/band_structure.py
pyprocar/cfg/band_structure_2d.py
pyprocar/cfg/band_structure_2d.yml
pyprocar/cfg/base.py
pyprocar/cfg/dos.py
pyprocar/cfg/dos.yml
pyprocar/cfg/fermi_surface_2d.py
pyprocar/cfg/fermi_surface_2d.yml
pyprocar/cfg/fermi_surface_3d.py
pyprocar/cfg/package.yml
pyprocar/cfg/unfold.py
pyprocar/cfg/unfold.yml
pyprocar/core/__init__.py
pyprocar/core/bandstructure2D.py
pyprocar/core/brillouin_zone.py
pyprocar/core/dos.py
pyprocar/core/ebs.py
pyprocar/core/fermisurface.py
pyprocar/core/fermisurface3D.py
pyprocar/core/fermisurface3Dnew.py
pyprocar/core/isosurface.py
pyprocar/core/kpath.py
pyprocar/core/procarselect.py
pyprocar/core/procarsymmetry.py
pyprocar/core/serializer.py
pyprocar/core/structure.py
pyprocar/core/surface.py
pyprocar/core/procarunfold/__init__.py
pyprocar/core/procarunfold/_bak.procarparser.py
pyprocar/core/procarunfold/fatband.py
pyprocar/core/procarunfold/procar_unfolder.py
pyprocar/core/procarunfold/unfolder.py
pyprocar/io/__init__.py
pyprocar/io/abinit.py
pyprocar/io/bxsf.py
pyprocar/io/dftbplus.py
pyprocar/io/elk.py
pyprocar/io/frmsf.py
pyprocar/io/lobster.py
pyprocar/io/parser.py
pyprocar/io/procarparser.py
pyprocar/io/qe.py
pyprocar/io/siesta.py
pyprocar/io/vasp.py
pyprocar/plotter/__init__.py
pyprocar/plotter/bs_2d_plot.py
pyprocar/plotter/dos_plot.py
pyprocar/plotter/ebs_plot.py
pyprocar/plotter/fermi3d_plot.py
pyprocar/plotter/procarplot.py
pyprocar/pyposcar/__init__.py
pyprocar/pyposcar/autoSelect.py
pyprocar/pyposcar/chg_raw.py
pyprocar/pyposcar/clusters.py
pyprocar/pyposcar/db.py
pyprocar/pyposcar/dbCovalentBond.py
pyprocar/pyposcar/defects.py
pyprocar/pyposcar/generalUtils.py
pyprocar/pyposcar/globalConectivity.py
pyprocar/pyposcar/honeycomb.py
pyprocar/pyposcar/latticeUtils.py
pyprocar/pyposcar/outcarParser.py
pyprocar/pyposcar/plot3d.py
pyprocar/pyposcar/plotBands.py
pyprocar/pyposcar/plotbands.py
pyprocar-6.5.0.dist-info/licenses/AUTHORS.rst
pyprocar-6.5.0.dist-info/licenses/LICENSE
pyprocar-6.5.0.dist-info/METADATA
pyprocar-6.5.0.dist-info/WHEEL
pyprocar-6.5.0.dist-info/entry_points.txt
pyprocar-6.5.0.dist-info/top_level.txt
pyprocar-6.5.0.dist-info/RECORD
