Metadata-Version: 2.4
Name: PyProcar
Version: 6.5.0
Summary: A Python library for electronic structure pre/post-processing.
Author: Reese Boucher, Freddy Farah
Author-email: Francisco Muñoz <fvmunoz@gmail.com>, Logan Lang <lllang@mix.wvu.edu>, Aldo Romero <alromero@mail.wvu.edu>, Sobhit Singh <smsingh@mix.wvu.edu>, Uthpala Herath <ukh0001@mix.wvu.edu>, Pedram Tavadze <petavazohi@mix.wvu.edu>, Eric Bousquet <eric.bousquet@uliege.be>, Xu He <mailhexu@gmail.com>
License:                   GNU GENERAL PUBLIC LICENSE
Project-URL: homepage, https://github.com/romerogroup/pyprocar
Project-URL: documentation, https://romerogroup.github.io/pyprocar/
Project-URL: Issues, https://github.com/romerogroup/pyprocar/issues
Project-URL: Changelog, https://github.com/romerogroup/pyprocar/CHANGELOG.md
Keywords: materials,science,plotting,electronic structure,DFT
Classifier: Programming Language :: Python :: 3
Requires-Python: >=3.8
License-File: LICENSE
License-File: AUTHORS.rst
Requires-Dist: matplotlib
Requires-Dist: numpy<2.0
Requires-Dist: pandas
Requires-Dist: scikit-image
Requires-Dist: scikit-learn
Requires-Dist: scipy
Requires-Dist: sympy
Requires-Dist: pyvista
Requires-Dist: trimesh
Requires-Dist: spglib
Requires-Dist: seekpath
Requires-Dist: ase
Requires-Dist: PyYAML
Requires-Dist: gdown
Requires-Dist: dill
Requires-Dist: variconfig
Requires-Dist: huggingface_hub[cli,hf_transfer]
Requires-Dist: pyvista[jupyter]
Provides-Extra: tests
Requires-Dist: pytest; extra == "tests"
Requires-Dist: pytest-cov; extra == "tests"
Requires-Dist: pymatgen; extra == "tests"
Requires-Dist: PyGithub; extra == "tests"
Provides-Extra: docs
Requires-Dist: sphinx_design; extra == "docs"
Requires-Dist: sphinx-copybutton; extra == "docs"
Requires-Dist: sphinx-gallery; extra == "docs"
Requires-Dist: numpydoc; extra == "docs"
Requires-Dist: pypandoc; extra == "docs"
Requires-Dist: pydata-sphinx-theme; extra == "docs"
Requires-Dist: sphinxcontrib-yaml; extra == "docs"
Requires-Dist: sphinxcontrib-autoyaml; extra == "docs"
Requires-Dist: python-dotenv; extra == "docs"
Requires-Dist: ipython; extra == "docs"
Requires-Dist: imageio-ffmpeg; extra == "docs"
Requires-Dist: sphinx; extra == "docs"
Requires-Dist: sphinx_rtd_theme; extra == "docs"
Requires-Dist: myst_parser; extra == "docs"
Requires-Dist: nbsphinx; extra == "docs"
Requires-Dist: sphinx-new-tab-link; extra == "docs"
Requires-Dist: sphinxcontrib-youtube; extra == "docs"
Requires-Dist: sphinxcontrib-video; extra == "docs"
Requires-Dist: pandoc; extra == "docs"
Requires-Dist: furo; extra == "docs"
Provides-Extra: dev
Requires-Dist: pyprocar[docs,tests]; extra == "dev"
Dynamic: license-file
